eidolon_ai_cli/StreamProcessor.py
eidolon_ai_cli/__init__.py
eidolon_ai_cli/auth_web_server.py
eidolon_ai_cli/client.py
eidolon_ai_cli/live_console.py
eidolon_ai_cli/main.py
eidolon_ai_cli/markdown.py
eidolon_ai_cli/schema.py
eidolon_ai_cli/security.py
eidolon_ai_cli/terminal2.py
eidolon_ai_cli/util.py
eidolon_ai_cli-0.1.2.dist-info/METADATA
eidolon_ai_cli-0.1.2.dist-info/WHEEL
eidolon_ai_cli-0.1.2.dist-info/entry_points.txt
eidolon_ai_cli-0.1.2.dist-info/RECORD
