Metadata-Version: 2.1
Name: eidolon-ai-cli
Version: 0.1.2
Summary: 
Author: Luke Lalor
Author-email: lukehlalor@gmail.com
Requires-Python: >=3.11,<4.0
Classifier: Programming Language :: Python :: 3
Classifier: Programming Language :: Python :: 3.11
Classifier: Programming Language :: Python :: 3.12
Requires-Dist: click (>=8.1.7,<9.0.0)
Requires-Dist: httpx (>=0.25.2,<0.26.0)
Requires-Dist: httpx-sse (>=0.4.0,<0.5.0)
Requires-Dist: markdown (>=3.5.2,<4.0.0)
Requires-Dist: mdit-py-plugins (>=0.4.0,<0.5.0)
Requires-Dist: prompt-toolkit (>=3.0.43,<4.0.0)
Requires-Dist: python-dotenv (>=1.0.1,<2.0.0)
Requires-Dist: requests (>=2.31.0,<3.0.0)
Requires-Dist: requests-oauthlib (>=1.3.1,<2.0.0)
Requires-Dist: rich (>=13.7.0,<14.0.0)
